{"pageContext":{"slug":"/post/2018-08-23-install-cuda-and-cudnn-on-ubuntu18.04/","category":"post","prev":null,"next":{"internal":{"content":"\nI decided to migrate my blog from hugo to gatsby.\nGatsby is based on react and misc plugins, and it works in the same way as normal web development. \nBut there are still some works to do, such as mathjax support.\n\n\n\n\n"},"fields":{"slug":"/post/2018-08-14-migrate-from-hugo-to-gatsby/","category":"post"},"frontmatter":{"title":"Migrate from Hugo to Gatsby","date":"2018-08-14T10:52:17Z","tags":null}}}}